odoo/addons/l10n_fi_business_code/README.rst
odoo/addons/l10n_fi_business_code/__init__.py
odoo/addons/l10n_fi_business_code/__manifest__.py
odoo/addons/l10n_fi_business_code/i18n/fi.po
odoo/addons/l10n_fi_business_code/i18n/l10n_fi_business_code.pot
odoo/addons/l10n_fi_business_code/models/__init__.py
odoo/addons/l10n_fi_business_code/models/res_partner.py
odoo/addons/l10n_fi_business_code/readme/CONFIGURE.rst
odoo/addons/l10n_fi_business_code/readme/CONTRIBUTORS.rst
odoo/addons/l10n_fi_business_code/readme/CREDITS.rst
odoo/addons/l10n_fi_business_code/readme/DESCRIPTION.rst
odoo/addons/l10n_fi_business_code/readme/HISTORY.rst
odoo/addons/l10n_fi_business_code/readme/MAINTAINER.rst
odoo/addons/l10n_fi_business_code/static/description/icon.png
odoo/addons/l10n_fi_business_code/static/description/index.html
odoo/addons/l10n_fi_business_code/tests/__init__.py
odoo/addons/l10n_fi_business_code/tests/test_partner.py
odoo/addons/l10n_fi_business_code/views/res_partner.xml
odoo14_addon_l10n_fi_business_code-14.0.1.0.1.dist-info/METADATA
odoo14_addon_l10n_fi_business_code-14.0.1.0.1.dist-info/WHEEL
odoo14_addon_l10n_fi_business_code-14.0.1.0.1.dist-info/top_level.txt
odoo14_addon_l10n_fi_business_code-14.0.1.0.1.dist-info/RECORD
