Metadata-Version: 2.1
Name: odoo14-addon-l10n-fi-business-code
Version: 14.0.1.0.1
Summary: Adds a business code (business id) for partners
Home-page: https://github.com/OCA/l10n-finland
Author: Tawasta, Odoo Community Association (OCA)
Author-email: support@odoo-community.org
License: LGPL-3
Platform: UNKNOWN
Classifier: Programming Language :: Python
Classifier: Framework :: Odoo
Classifier: Framework :: Odoo :: 14.0
Classifier: License :: OSI Approved :: GNU Lesser General Public License v3 (LGPLv3)
Classifier: Development Status :: 5 - Production/Stable
Requires-Python: >=3.6
Requires-Dist: odoo <14.1dev,>=14.0a
